botocove/__init__.py
botocove/cove_decorator.py
botocove/cove_host_account.py
botocove/cove_runner.py
botocove/cove_session.py
botocove/cove_types.py
botocove/py.typed
botocove-1.7.4.dist-info/LICENSE
botocove-1.7.4.dist-info/METADATA
botocove-1.7.4.dist-info/WHEEL
botocove-1.7.4.dist-info/RECORD
