Metadata-Version: 2.1
Name: botocove
Version: 1.7.4
Summary: A decorator to allow running a function against all AWS accounts in an organization
Home-page: https://github.com/connelldave/botocove
License: LGPL-3.0-or-later
Keywords: AWS,organizations,AWS organizations,boto3
Author: Dave Connell
Author-email: daveconn41@gmail.com
Requires-Python: >=3.8,<4.0
Classifier: License :: OSI Approved :: GNU Lesser General Public License v3 or later (LGPLv3+)
Classifier: Programming Language :: Python :: 3
Classifier: Programming Language :: Python :: 3.8
Classifier: Programming Language :: Python :: 3.9
Classifier: Programming Language :: Python :: 3.10
Classifier: Programming Language :: Python :: 3.11
Classifier: Programming Language :: Python :: 3.12
Requires-Dist: boto3
Requires-Dist: boto3-stubs[organizations,sts]
Requires-Dist: tqdm
Requires-Dist: types-tqdm
Project-URL: Repository, https://github.com/connelldave/botocove
